psychofit.py
Psychofit-1.0.0.post0.dist-info/LICENSE
Psychofit-1.0.0.post0.dist-info/METADATA
Psychofit-1.0.0.post0.dist-info/WHEEL
Psychofit-1.0.0.post0.dist-info/top_level.txt
Psychofit-1.0.0.post0.dist-info/RECORD
