Metadata-Version: 2.1
Name: Psychofit
Version: 1.0.0.post0
Summary: A module for fitting 2AFC psychometric data
Home-page: https://github.com/cortex-lab/psychofit
Author: Matteo Carandini & Miles Wells
License: MIT
Platform: UNKNOWN
Classifier: Programming Language :: Python :: 3
Classifier: License :: OSI Approved :: MIT License
Classifier: Operating System :: OS Independent
Requires-Python: >=3.7
License-File: LICENSE
